pythonvideoannotator_module_distances/__init__.py
pythonvideoannotator_module_distances/distances_window.py
pythonvideoannotator_module_distances/module.py
Python_video_annotator_module_distances-0.5.18.dist-info/METADATA
Python_video_annotator_module_distances-0.5.18.dist-info/WHEEL
Python_video_annotator_module_distances-0.5.18.dist-info/top_level.txt
Python_video_annotator_module_distances-0.5.18.dist-info/RECORD
